bleach-stubs/METADATA.toml
bleach-stubs/__init__.pyi
bleach-stubs/callbacks.pyi
bleach-stubs/css_sanitizer.pyi
bleach-stubs/html5lib_shim.pyi
bleach-stubs/linkifier.pyi
bleach-stubs/parse_shim.pyi
bleach-stubs/py.typed
bleach-stubs/sanitizer.pyi
types_bleach-6.2.0.20250512.dist-info/licenses/LICENSE
types_bleach-6.2.0.20250512.dist-info/METADATA
types_bleach-6.2.0.20250512.dist-info/WHEEL
types_bleach-6.2.0.20250512.dist-info/top_level.txt
types_bleach-6.2.0.20250512.dist-info/RECORD
